MANIFEST.in
README.rst
VERSION
aws_lambda_logging.py
setup.cfg
setup.py
aws_lambda_logger_for_python.egg-info/PKG-INFO
aws_lambda_logger_for_python.egg-info/SOURCES.txt
aws_lambda_logger_for_python.egg-info/dependency_links.txt
aws_lambda_logger_for_python.egg-info/requires.txt
aws_lambda_logger_for_python.egg-info/top_level.txt