Metadata-Version: 2.1
Name: aws-lambda-logger-for-python
Version: 0.2.0
Summary: Nanolib to enhance logging in aws lambda
Home-page: https://github.com/Marcin-Duszynski/aws-lambda-logger-for-python
License: MIT
Platform: UNKNOWN
Classifier: Development Status :: 3 - Alpha
Classifier: Intended Audience :: Developers
Classifier: License :: OSI Approved :: MIT License
Classifier: Programming Language :: Python :: 3.6
Provides-Extra: dev
Provides-Extra: tests
